create_gitlab_project/__init__.py
create_gitlab_project/__main__.py
create_gitlab_project/cli.py
create_gitlab_project/constants.py
create_gitlab_project/create_gitlab_project_dfx.py
create_gitlab_project/template-files/Jenkinsfile
create_gitlab_project/template-files/README.md
create_gitlab_project-0.0.1.dist-info/METADATA
create_gitlab_project-0.0.1.dist-info/WHEEL
create_gitlab_project-0.0.1.dist-info/top_level.txt
create_gitlab_project-0.0.1.dist-info/RECORD
